oemthermostat/__init__.py
oemthermostat/client.py
oemthermostat/tests/__init__.py
oemthermostat/tests/test_thermostat.py
oemthermostat-1.1.1.dist-info/LICENSE.md
oemthermostat-1.1.1.dist-info/METADATA
oemthermostat-1.1.1.dist-info/WHEEL
oemthermostat-1.1.1.dist-info/top_level.txt
oemthermostat-1.1.1.dist-info/RECORD
