Metadata-Version: 2.1
Name: oemthermostat
Version: 1.1.1
Summary: A package to interface with the HTTP API of the OpenEnergyMonitor Thermostat.
Home-page: https://github.com/Cadair/openenergymonitor_thermostat
Author: "Stuart Mumford"
Author-email: "stuart@cadair.com"
License: BSD
Platform: UNKNOWN
Classifier: Programming Language :: Python :: 3
Provides-Extra: test
Provides-Extra: docs
